[
  {
    "id": "especialista-em-emboscada",
    "name": "Especialista em Emboscada",
    "type": "Habilidades de Geckos",
    "description": "A figura com essa habilidade pode ser posicionada no começo do jogo em qualquer lugar do tabuleiro, contanto que fora da linha de visão de todas as figuras inimigas e a mais de 30cm de todas as figuras inimigas. Durante sua primeira ativação, qualquer ataque de uma figura posicionada dessa forma tem um modificador de dano de +2 contra figuras que ainda não ativaram."
  },
  {
    "id": "movimentação-furtiva",
    "name": "Movimentação Furtiva",
    "type": "Habilidades de Geckos",
    "description": "A figura com essa habilida ganha +2 no seu teste de Ímpeto para se defender de ataques a distância se estiver em cobertura."
  }
]