[{
    "name": "Nevasca",
    "castingNumber": 8,
    "keywords": ["Área de Efeito(Zona Pequena)", "Concentração"],
    "effect": "Centralize a Zona no Sacerdote e mova-a junto com ele. Figuras na área de efeito tem =2 de Ímpeto."
},
{
    "name": "Impacto Estrondoso",
    "castingNumber": 16,
    "keywords": ["Alcance(30cm)"],
    "effect": "A figura alvo imediatamente sofre um Ataque Gélido +5 com a palavra chave Concussiva(4)"
},
{
    "name": "Fúria Lupina",
    "castingNumber": 12,
    "keywords": ["Conjurador Apenas", "Concentração"],
    "effect": "O Sacerdote ganha a característica Forte, e causa um dano crítico em uma rolagem de 18, 19 ou 20."
},
{
    "name": "Voracidade do Predador",
    "castingNumber": 10,
    "keywords": ["Linha de Visão"],
    "effect": "A figura aliada alvo ganha a característica Fúria até o final do jogo."
},
{
    "name": "Uivo de Ulric",
    "castingNumber": 16,
    "keywords": ["Conjurador Apenas"],
    "effect": "Durante a duração da batalha, todas as figuras do bando do sacerdote são Imunes a Aterrorizante. Adicionalmente, o bando ganha +3 em testes de debandada."
},
{
    "name": "Chamado de Ulric",
    "castingNumber": 16,
    "keywords": ["Conjurador Apenas"],
    "effect": "O sacerdote se transforma em um Grande Lobo Branco,  tendo Movimento 17 Ímpeto +4, Precisão 0, Armadura 10, Vontade +1 e Vida 14, ganhando a característica Forte. Durante seu tempo como lobo ele não se aproveita dos efeitos de itens e não pode conjurar magias. Em cada uma de suas ativações, ele pode fazer um teste de Vontade com CD igual a classe de dificuldade dessa magia para voltar a sua forma humana caso tenha sucessa. Se terminar um jogo transformado em lobo, ele pode fazer o teste uma última vez. Em caso de falha, se torna um lobo permanentemente, usando os seguintes status: Movimento 22, Ímpeto 7, Precisão 0, Armadura 10, Vontade +2 e Vida 22. Ele ganha as características Voraz e Animal. Embora se mantenha um héroi, ele não pode mais ganhar experiência e perde todos os seus avanços, também não podendo mais realizar atividades para o bando., mas continua contando como um héroi."
}
]